django_meilisearch/__init__.py
django_meilisearch/apps.py
django_meilisearch/exceptions.py
django_meilisearch/indexes.py
django_meilisearch/management/__init__.py
django_meilisearch/management/commands/__init__.py
django_meilisearch/management/commands/meilisearch.py
django_meilisearch/metaclass.py
django_meilisearch/serializers/core.py
django_meilisearch/serializers/drf.py
django_meilisearch/serializers/facade.py
django_meilisearch/templates/django_meilisearch/base/base.html
django_meilisearch/tests/__init__.py
django_meilisearch/tests/test_serializers/__init__.py
django_meilisearch/tests/test_serializers/test_timestampfield_serializer.py
django_meilisearch/tests/test_utils/__init__.py
django_meilisearch/tests/test_utils/test_exists_field_in_namespace.py
django_meilisearch/tests/test_utils/test_get_datetime_fields.py
django_meilisearch/tests/test_validators/__init__.py
django_meilisearch/tests/test_validators/test_validate_drf_serializer.py
django_meilisearch/tests/test_validators/test_validate_filterable_fields.py
django_meilisearch/tests/test_validators/test_validate_searchable_fields.py
django_meilisearch/tests/test_validators/test_validate_sortable_fields.py
django_meilisearch/types.py
django_meilisearch/utils.py
django_meilisearch/validators.py
django_meilisearch-0.2.0.dist-info/METADATA
django_meilisearch-0.2.0.dist-info/WHEEL
django_meilisearch-0.2.0.dist-info/entry_points.txt
django_meilisearch-0.2.0.dist-info/licenses/LICENSE
django_meilisearch-0.2.0.dist-info/RECORD
