Metadata-Version: 2.4
Name: django-meilisearch
Version: 0.2.0
Summary: 
License-File: LICENSE
Author: Lucas Rocha
Author-email: lucash.rocha@hotmail.com>
Requires-Python: >=3.11,<4
Classifier: Programming Language :: Python :: 3
Classifier: Programming Language :: Python :: 3.11
Classifier: Programming Language :: Python :: 3.12
Classifier: Programming Language :: Python :: 3.13
Classifier: Programming Language :: Python :: 3.14
Requires-Dist: alive-progress (>=3.1.5)
Requires-Dist: camel-converter (>=4.0)
Requires-Dist: django (>=4)
Requires-Dist: djangorestframework (>=3.15.2)
Requires-Dist: meilisearch (>=0.31.4)
Requires-Dist: python-dotenv (>=1.2.1,<2.0.0)
